Metadata-Version: 2.1
Name: binary-formatter-468
Version: 0.0.2
Summary: Badly Made Binary Formatter
Home-page: UNKNOWN
Author: joseph_468
License: UNKNOWN
Platform: UNKNOWN
